shell_mcp_server/__init__.py
shell_mcp_server/config.py
shell_mcp_server/server.py
shell_mcp_server-0.1.0.dist-info/METADATA
shell_mcp_server-0.1.0.dist-info/WHEEL
shell_mcp_server-0.1.0.dist-info/entry_points.txt
shell_mcp_server-0.1.0.dist-info/RECORD
