Metadata-Version: 2.3
Name: shell-mcp-server
Version: 0.1.0
Summary: Shell MCP Server for Claude AI Application
Author-email: blazickjp <joe.blazick@yahoo.com>
Requires-Python: >=3.11
Requires-Dist: mcp>=1.0.0
Requires-Dist: pydantic-settings>=2.0.0
Requires-Dist: pydantic>=2.0.0
Provides-Extra: test
Requires-Dist: pytest-asyncio>=0.23.0; extra == 'test'
Requires-Dist: pytest-cov>=4.1.0; extra == 'test'
Requires-Dist: pytest>=7.0.0; extra == 'test'
